MANIFEST.in
setup.py
../../utilities/__init__.py
../../utilities/andorgui.py
../../utilities/camdisp.py
../../utilities/interruptable_region.py
../../utilities/logging.py
../../utilities/misc.py
../../utilities/plotting.py
../../utilities/pxlflygui.py
../../utilities/setup-thermistor.py
../../utilities/terminal.py
mccdaq/__init__.py
mccdaq/usb2600/__init__.py
mccdaq/usb2600/mccdaq-extra.c
mccdaq/usb2600/mccdaq-extra.h
mccdaq/usb2600/setup_extension.py
mccdaq/usb2600/usb2600.c
mccdaq/usb2600/usb2600.pxd
mccdaq/usb2600/usb2600.py
mccdaq/usb2600/usb2600.pyx
mccdaq/utilities/__init__.py
mccdaq/utilities/waveform.py
mccdaq_linux.egg-info/PKG-INFO
mccdaq_linux.egg-info/SOURCES.txt
mccdaq_linux.egg-info/dependency_links.txt
mccdaq_linux.egg-info/requires.txt
mccdaq_linux.egg-info/top_level.txt