Metadata-Version: 1.1
Name: mccdaq-linux
Version: 1.4.8
Summary: Python drivers for Measurement Computing devices (mccdaq.com) on linux
Home-page: UNKNOWN
Author: Guillaume Lepert
Author-email: guillaume.lepert07@imperial.ac.uk
License: UNKNOWN
Platform: linux
Classifier: Development Status :: 5 - Production/Stable
Classifier: Environment :: Console
Classifier: Intended Audience :: Science/Research
Classifier: License :: OSI Approved :: MIT License
Classifier: Natural Language :: English
Classifier: Operating System :: POSIX :: Linux
Classifier: Programming Language :: C
Classifier: Programming Language :: Cython
Classifier: Programming Language :: Python :: 2.7
Classifier: Topic :: Home Automation
Classifier: Topic :: Scientific/Engineering
